scsarchive/__init__.py
scsarchive/core.py
scsarchive-1.0.6.dist-info/LICENSE
scsarchive-1.0.6.dist-info/METADATA
scsarchive-1.0.6.dist-info/WHEEL
scsarchive-1.0.6.dist-info/top_level.txt
scsarchive-1.0.6.dist-info/RECORD
