Metadata-Version: 2.1
Name: scsarchive
Version: 1.0.6
Summary: A Python archive format plugin for creating uncompressed SCS (Euro Truck Simulator 2 mod) archives.
Author-email: Allie Nikol Modern <a.modern.freelancing@gmail.com>
License: MIT
Project-URL: Homepage, https://github.com/Lil-Allie-Astra/scsarchive
Project-URL: Bug Tracker, https://github.com/Lil-Allie-Astra/scsarchive/issues
Classifier: Programming Language :: Python :: 3
Classifier: Programming Language :: Python :: 3.7
Classifier: Programming Language :: Python :: 3.8
Classifier: Programming Language :: Python :: 3.9
Classifier: Programming Language :: Python :: 3.10
Classifier: Programming Language :: Python :: 3.11
Classifier: Programming Language :: Python :: 3.12
License-File: LICENSE
